llama_index/llms/cloudflare_ai_gateway/__init__.py
llama_index/llms/cloudflare_ai_gateway/base.py
llama_index/llms/cloudflare_ai_gateway/providers.py
llama_index_llms_cloudflare_ai_gateway-0.2.1.dist-info/METADATA
llama_index_llms_cloudflare_ai_gateway-0.2.1.dist-info/WHEEL
llama_index_llms_cloudflare_ai_gateway-0.2.1.dist-info/RECORD
