Metadata-Version: 2.4
Name: llama-index-llms-cloudflare-ai-gateway
Version: 0.2.1
Summary: llama-index llms cloudflare ai gateway integration
Author-email: Chojan Shang <psiace@outlook.com>
Maintainer: psiace
License-Expression: MIT
Keywords: ai,cloudflare,gateway
Requires-Python: <4.0,>=3.10
Requires-Dist: httpx<1,>=0.24.0
Requires-Dist: llama-index-core<0.15,>=0.13.0
